hfut_brush/__init__.py
hfut_brush/bru.py
hfut_brush-0.1.0.dist-info/DESCRIPTION.rst
hfut_brush-0.1.0.dist-info/METADATA
hfut_brush-0.1.0.dist-info/RECORD
hfut_brush-0.1.0.dist-info/WHEEL
hfut_brush-0.1.0.dist-info/entry_points.txt
hfut_brush-0.1.0.dist-info/metadata.json
hfut_brush-0.1.0.dist-info/top_level.txt
test/__init__.py
test/test_login.py
