Metadata-Version: 2.0
Name: hfut-brush
Version: 0.1.0
Summary: Tool for HFUT students
Home-page: https://github.com/Jie-OY/hfut_brush
Author: W@I@S@E
Author-email: wisecsj@gmail.com
License: GNU GPL 3
Keywords: hfut auto-complete tool
Platform: UNKNOWN
Classifier: Programming Language :: Python :: 3.4
Classifier: Programming Language :: Python :: 3.5
Classifier: Programming Language :: Python :: 3.6
Requires-Python: >=3
Requires-Dist: beautifulsoup4
Requires-Dist: requests
Requires-Dist: xlrd
